grpc_kit/__init__.py
grpc_kit/client.py
grpc_kit/decorator.py
grpc_kit/server.py
grpc_kit/utils.py
grpc_kit-0.1.41.dist-info/METADATA
grpc_kit-0.1.41.dist-info/WHEEL
grpc_kit-0.1.41.dist-info/RECORD
